sp2ts/__init__.py
sp2ts/get_transition_dates.py
sp2ts/sp2ts.py
tests/test_sp2ts.py
sp2ts-1.0.0.dist-info/LICENSE
sp2ts-1.0.0.dist-info/METADATA
sp2ts-1.0.0.dist-info/WHEEL
sp2ts-1.0.0.dist-info/entry_points.txt
sp2ts-1.0.0.dist-info/top_level.txt
sp2ts-1.0.0.dist-info/RECORD
