Metadata-Version: 2.1
Name: sp2ts
Version: 1.0.0
Summary: Convert between the settlement periods used by GB electricity industry and Unix timestamps.
Author-email: Jamie Taylor <jamie.taylor@sheffield.ac.uk>
Maintainer-email: Jamie Taylor <jamie.taylor@sheffield.ac.uk>
Project-URL: Homepage, https://github.com/SheffieldSolar/sp2ts
Project-URL: Documentation, https://sheffieldsolar.github.io/PV_Live-API/build/html/index.html
Project-URL: Repository, https://github.com/SheffieldSolar/sp2ts
Project-URL: Bug Tracker, https://github.com/SheffieldSolar/sp2ts/issues
Keywords: timestamp,timezone,settlement period,settlement date,settlement time,electricity market
Classifier: Development Status :: 4 - Beta
Classifier: Intended Audience :: Developers
Classifier: Intended Audience :: Science/Research
Classifier: Intended Audience :: System Administrators
Classifier: Topic :: Database :: Database Engines/Servers
Classifier: Topic :: Utilities
Classifier: Programming Language :: Python
Classifier: Programming Language :: Python :: 3
Classifier: Programming Language :: Python :: 3.9
Classifier: Programming Language :: Python :: 3.10
Classifier: Programming Language :: Python :: 3.11
Classifier: Programming Language :: Python :: 3.12
Requires-Python: >=3.9
License-File: LICENSE
Requires-Dist: pytz
Requires-Dist: numpy
